echoes_mcp/__init__.py
echoes_mcp/cli.py
echoes_mcp/server.py
echoes_mcp/database/__init__.py
echoes_mcp/database/lancedb.py
echoes_mcp/database/schemas.py
echoes_mcp/indexer/__init__.py
echoes_mcp/indexer/embeddings.py
echoes_mcp/indexer/extractor.py
echoes_mcp/indexer/scanner.py
echoes_mcp/indexer/spacy_utils.py
echoes_mcp/prompts/__init__.py
echoes_mcp/prompts/handlers.py
echoes_mcp/prompts/substitution.py
echoes_mcp/prompts/validation.py
echoes_mcp/tools/__init__.py
echoes_mcp/tools/index.py
echoes_mcp/tools/search.py
echoes_mcp/tools/stats.py
echoes_mcp/tools/words_count.py
echoes_mcp_server-5.8.1.dist-info/METADATA
echoes_mcp_server-5.8.1.dist-info/WHEEL
echoes_mcp_server-5.8.1.dist-info/entry_points.txt
echoes_mcp_server-5.8.1.dist-info/licenses/LICENSE
echoes_mcp_server-5.8.1.dist-info/RECORD
