Metadata-Version: 2.4
Name: echoes-mcp-server
Version: 5.8.1
Summary: MCP server for Echoes storytelling platform with Narrative Knowledge Graph
Project-URL: Homepage, https://github.com/echoes-io/mcp-server
Project-URL: Repository, https://github.com/echoes-io/mcp-server
Project-URL: Issues, https://github.com/echoes-io/mcp-server/issues
Author-email: Zweer <n.olivieriachille@gmail.com>
License: MIT
License-File: LICENSE
Keywords: echoes,knowledge-graph,llm,mcp,rag,storytelling
Classifier: Development Status :: 3 - Alpha
Classifier: Intended Audience :: Developers
Classifier: License :: OSI Approved :: MIT License
Classifier: Programming Language :: Python :: 3.11
Classifier: Programming Language :: Python :: 3.12
Classifier: Topic :: Scientific/Engineering :: Artificial Intelligence
Requires-Python: >=3.11
Requires-Dist: click>=8.1
Requires-Dist: google-genai>=1.56.0
Requires-Dist: lancedb>=0.17
Requires-Dist: llama-index-embeddings-huggingface>=0.4
Requires-Dist: llama-index>=0.12
Requires-Dist: mcp>=1.0
Requires-Dist: pydantic>=2.0
Requires-Dist: pyyaml>=6.0
Requires-Dist: rich>=13.0
Requires-Dist: sentence-transformers>=3.0
Requires-Dist: spacy>=3.7
Requires-Dist: torch>=2.0
Provides-Extra: dev
Requires-Dist: mypy>=1.13; extra == 'dev'
Requires-Dist: pytest-asyncio>=0.24; extra == 'dev'
Requires-Dist: pytest-cov>=6.0; extra == 'dev'
Requires-Dist: pytest>=8.0; extra == 'dev'
Requires-Dist: python-semantic-release>=9.0; extra == 'dev'
Requires-Dist: ruff>=0.8; extra == 'dev'
